mycroft/__init__.py
mycroft/api/__init__.py
mycroft/audio/__init__.py
mycroft/audio/__main__.py
mycroft/audio/audioservice.py
mycroft/audio/speech.py
mycroft/audio/services/__init__.py
mycroft/audio/services/chromecast/__init__.py
mycroft/audio/services/mopidy/__init__.py
mycroft/audio/services/mopidy/mopidypost.py
mycroft/audio/services/mplayer/__init__.py
mycroft/audio/services/simple/__init__.py
mycroft/audio/services/vlc/__init__.py
mycroft/client/__init__.py
mycroft/client/enclosure/__init__.py
mycroft/client/enclosure/__main__.py
mycroft/client/enclosure/base.py
mycroft/client/enclosure/generic/__init__.py
mycroft/client/enclosure/mark1/__init__.py
mycroft/client/enclosure/mark1/arduino.py
mycroft/client/enclosure/mark1/eyes.py
mycroft/client/enclosure/mark1/mouth.py
mycroft/client/enclosure/mark2/__init__.py
mycroft/client/speech/__init__.py
mycroft/client/speech/__main__.py
mycroft/client/speech/hotword_factory.py
mycroft/client/speech/listener.py
mycroft/client/speech/mic.py
mycroft/client/speech/snowboydecoder.py
mycroft/client/speech/snowboydetect.py
mycroft/client/speech/word_extractor.py
mycroft/client/speech/recognizer/__init__.py
mycroft/client/text/__init__.py
mycroft/client/text/__main__.py
mycroft/client/text/gui_server.py
mycroft/client/text/text_client.py
mycroft/configuration/__init__.py
mycroft/configuration/config.py
mycroft/configuration/locations.py
mycroft/dialog/__init__.py
mycroft/enclosure/__init__.py
mycroft/enclosure/api.py
mycroft/enclosure/display_manager.py
mycroft/filesystem/__init__.py
mycroft/identity/__init__.py
mycroft/lock/__init__.py
mycroft/messagebus/__init__.py
mycroft/messagebus/message.py
mycroft/messagebus/send.py
mycroft/messagebus/client/__init__.py
mycroft/messagebus/client/ws.py
mycroft/messagebus/service/__init__.py
mycroft/messagebus/service/__main__.py
mycroft/messagebus/service/ws.py
mycroft/metrics/__init__.py
mycroft/session/__init__.py
mycroft/skills/__init__.py
mycroft/skills/__main__.py
mycroft_ekylibre_utils-0.9.dist-info/LICENSE
mycroft_ekylibre_utils-0.9.dist-info/METADATA
mycroft_ekylibre_utils-0.9.dist-info/WHEEL
mycroft_ekylibre_utils-0.9.dist-info/top_level.txt
mycroft_ekylibre_utils-0.9.dist-info/RECORD
