Metadata-Version: 2.1
Name: mycroft-ekylibre-utils
Version: 0.9
Summary: Ekylibre set of tools for MycroftAI skills
Home-page: http://github.com/ekylibre
Author: Ekylibre
Author-email: rdechazelles@ekylibre.com
License: UNKNOWN
Platform: UNKNOWN
Classifier: Programming Language :: Python :: 3
Classifier: License :: OSI Approved :: Apache Software License
Classifier: Operating System :: OS Independent
